ava_protocol_sdk/__init__.py
ava_protocol_sdk/client.py
ava_protocol_sdk/avsproto/__init__.py
ava_protocol_sdk/avsproto/avs_pb2.py
ava_protocol_sdk/avsproto/avs_pb2_grpc.py
ava_protocol_sdk-0.1.0.dist-info/LICENSE
ava_protocol_sdk-0.1.0.dist-info/METADATA
ava_protocol_sdk-0.1.0.dist-info/WHEEL
ava_protocol_sdk-0.1.0.dist-info/top_level.txt
ava_protocol_sdk-0.1.0.dist-info/RECORD
